mcp_aktools/__init__.py
mcp_aktools/__main__.py
mcp_aktools/cache.py
mcp_aktools-0.1.14.dist-info/METADATA
mcp_aktools-0.1.14.dist-info/WHEEL
mcp_aktools-0.1.14.dist-info/entry_points.txt
mcp_aktools-0.1.14.dist-info/licenses/LICENSE
mcp_aktools-0.1.14.dist-info/RECORD
