Metadata-Version: 2.4
Name: mcp-aktools
Version: 0.1.14
Summary: MCP Server for stock and crypto
Project-URL: Homepage, https://github.com/aahl/mcp-aktools
Project-URL: Repository, https://github.com/aahl/mcp-aktools.git
License: MIT
License-File: LICENSE
Keywords: akshare,aktools,llm,mcp,stock,trading
Requires-Python: >=3.10
Requires-Dist: akshare>=1.17.0
Requires-Dist: cachetools>=6.2.0
Requires-Dist: diskcache>=5.6.0
Requires-Dist: fastmcp>=2.0.0
